{"name":"images","projectId":"images","type":"CONCERT","status":"STAGE4_SEATS_READY","currentStage":"4","stage5Saved":false,"sectionCount":0,"seatCount":0,"bookingButtonCount":0,"folderName":"images","sourceFileName":"images.png","createdAt":"2026-07-02T10:46:15.387143400","updatedAt":"2026-07-02T10:48:05.255574200","files":{"originalImage":"original-image.png","croppedImage":"cropped-image.png","seatmapImage":"seatmap-image.png","stage5Image":"seatmap-stage5.png","finalImage":"seatmap-final.png","buttonImage":"button-image.png","thumbnail":"thumbnail.png","debugPolygons":"debug-polygons.png","sections":"seatmap-sections.json","bookingButtons":"booking-buttons.json","decorations":"seatmap-decorations.json","style":"seatmap-style.json","seats":"/temp/seatmap/images/seats/index.json","legacySeats":"/temp/seatmap/seats/images-seatmap-seats.json"}}